mcp_windows/__init__.py
mcp_windows/appid.py
mcp_windows/clipboard.py
mcp_windows/main.py
mcp_windows/media.py
mcp_windows/monitors.py
mcp_windows/notifications.py
mcp_windows/screenshot.py
mcp_windows/startmenu.py
mcp_windows/theme.py
mcp_windows/window_management.py
mcp_windows-0.1.0.dist-info/METADATA
mcp_windows-0.1.0.dist-info/WHEEL
mcp_windows-0.1.0.dist-info/entry_points.txt
mcp_windows-0.1.0.dist-info/licenses/LICENSE
mcp_windows-0.1.0.dist-info/RECORD
