Metadata-Version: 2.4
Name: mcp-windows
Version: 0.1.0
Summary: MCP server for the windows API.
Project-URL: Homepage, https://github.com/SecretiveShell/mcp-windows
Project-URL: Documentation, https://github.com/SecretiveShell/mcp-windows
Project-URL: Repository, https://github.com/SecretiveShell/mcp-windows.git
Project-URL: Issues, https://github.com/SecretiveShell/mcp-windows/issues
Project-URL: Changelog, https://github.com/SecretiveShell/mcp-windows/commits/master/
Author-email: TerminalMan <84923604+SecretiveShell@users.noreply.github.com>
License-File: LICENSE
Requires-Python: >=3.13
Requires-Dist: fastmcp>=2.2.0
Requires-Dist: mcp>=1.6.0
Requires-Dist: pillow>=11.2.1
Requires-Dist: psutil>=7.0.0
Requires-Dist: pywin32>=310
Requires-Dist: winrt-runtime>=3.1.0
Requires-Dist: winrt-windows-data-xml-dom>=3.1.0
Requires-Dist: winrt-windows-foundation-collections>=3.1.0
Requires-Dist: winrt-windows-foundation>=3.1.0
Requires-Dist: winrt-windows-media-control>=3.1.0
Requires-Dist: winrt-windows-storage>=3.1.0
Requires-Dist: winrt-windows-system>=3.1.0
Requires-Dist: winrt-windows-ui-notifications>=3.1.0
